tibert/__init__.py
tibert/bertcoref.py
tibert/predict.py
tibert/py.typed
tibert/run_test.py
tibert/run_train.py
tibert/score.py
tibert/train.py
tibert/utils.py
tibert-0.5.2.dist-info/LICENSE
tibert-0.5.2.dist-info/METADATA
tibert-0.5.2.dist-info/WHEEL
tibert-0.5.2.dist-info/RECORD
