Metadata-Version: 2.1
Name: tibert
Version: 0.5.2
Summary: BERT for Coreference Resolution
License: GPL-3.0-only
Author: Arthur Amalvy
Author-email: arthur.amalvy@univ-avignon.fr
Requires-Python: >=3.8,<3.13
Classifier: License :: OSI Approved :: GNU General Public License v3 (GPLv3)
Classifier: Programming Language :: Python :: 3
Classifier: Programming Language :: Python :: 3.8
Classifier: Programming Language :: Python :: 3.9
Classifier: Programming Language :: Python :: 3.10
Classifier: Programming Language :: Python :: 3.11
Classifier: Programming Language :: Python :: 3.12
Requires-Dist: more-itertools (>=10.5,<11.0)
Requires-Dist: neleval (>=3.1.1,<4.0.0)
Requires-Dist: networkx (>=3.0,<4.0)
Requires-Dist: rich (>=13.5,<14.0)
Requires-Dist: sacremoses (>=0.1,<0.2)
Requires-Dist: torch (>=2.0.0,!=2.0.1)
Requires-Dist: tqdm (>=4.67,<5.0)
Requires-Dist: transformers (>=4.32,<5.0)
